cnrm_pydantic_models-0.4.0.dist-info/METADATA
cnrm_pydantic_models-0.4.0.dist-info/WHEEL
cnrm_pydantic_models/__init__.py
cnrm_pydantic_models/accesscontextmanageraccesslevel.py
cnrm_pydantic_models/accesscontextmanageraccesslevelcondition.py
cnrm_pydantic_models/accesscontextmanageraccesspolicy.py
cnrm_pydantic_models/accesscontextmanagergcpuseraccessbinding.py
cnrm_pydantic_models/accesscontextmanagerserviceperimeter.py
cnrm_pydantic_models/accesscontextmanagerserviceperimeterresource.py
cnrm_pydantic_models/alloydbbackup.py
cnrm_pydantic_models/alloydbcluster.py
cnrm_pydantic_models/alloydbinstance.py
cnrm_pydantic_models/alloydbuser.py
cnrm_pydantic_models/apigatewayapi.py
cnrm_pydantic_models/apigatewayapiconfig.py
cnrm_pydantic_models/apigatewaygateway.py
cnrm_pydantic_models/apigeeaddonsconfig.py
cnrm_pydantic_models/apigeeendpointattachment.py
cnrm_pydantic_models/apigeeenvgroup.py
cnrm_pydantic_models/apigeeenvgroupattachment.py
cnrm_pydantic_models/apigeeenvironment.py
cnrm_pydantic_models/apigeeinstance.py
cnrm_pydantic_models/apigeeinstanceattachment.py
cnrm_pydantic_models/apigeenataddress.py
cnrm_pydantic_models/apigeeorganization.py
cnrm_pydantic_models/apigeesyncauthorization.py
cnrm_pydantic_models/appenginedomainmapping.py
cnrm_pydantic_models/appenginefirewallrule.py
cnrm_pydantic_models/appengineflexibleappversion.py
cnrm_pydantic_models/appengineservicesplittraffic.py
cnrm_pydantic_models/appenginestandardappversion.py
cnrm_pydantic_models/artifactregistryrepository.py
cnrm_pydantic_models/beyondcorpappconnection.py
cnrm_pydantic_models/beyondcorpappconnector.py
cnrm_pydantic_models/beyondcorpappgateway.py
cnrm_pydantic_models/bigqueryanalyticshubdataexchange.py
cnrm_pydantic_models/bigqueryanalyticshublisting.py
cnrm_pydantic_models/bigqueryconnectionconnection.py
cnrm_pydantic_models/bigquerydatapolicydatapolicy.py
cnrm_pydantic_models/bigquerydataset.py
cnrm_pydantic_models/bigquerydatasetaccess.py
cnrm_pydantic_models/bigquerydatatransferconfig.py
cnrm_pydantic_models/bigqueryjob.py
cnrm_pydantic_models-0.4.0.dist-info/RECORD
